fuzz/__init__.py
fuzz/values.py
fuzz-0.1.0.dist-info/DESCRIPTION.rst
fuzz-0.1.0.dist-info/METADATA
fuzz-0.1.0.dist-info/RECORD
fuzz-0.1.0.dist-info/WHEEL
fuzz-0.1.0.dist-info/metadata.json
fuzz-0.1.0.dist-info/top_level.txt
